clustats/__init__.py
clustats/format_latex.py
clustats/runstats.py
clustats-0.0.9.dist-info/entry_points.txt
clustats-0.0.9.dist-info/WHEEL
clustats-0.0.9.dist-info/METADATA
clustats-0.0.9.dist-info/RECORD
